dockerbuild_images/__init__.py
dockerbuild_images/base.py
dockerbuild_images/cli.py
dockerbuild_images/config_reader.py
dockerbuild_images/dependency.py
dockerbuild_images/pyimporter.py
dockerbuild_images-0.0.10.dist-info/LICENSE
dockerbuild_images-0.0.10.dist-info/METADATA
dockerbuild_images-0.0.10.dist-info/WHEEL
dockerbuild_images-0.0.10.dist-info/entry_points.txt
dockerbuild_images-0.0.10.dist-info/top_level.txt
dockerbuild_images-0.0.10.dist-info/RECORD
