Metadata-Version: 2.1
Name: dockerbuild-images
Version: 0.0.10
Summary: Recursively builds Dockerfiles
Home-page: https://github.com/jqb/dockerbuild-images
Author: Jakub Janoszek
Author-email: kuba.janoszek@gmail.com
License: UNKNOWN
Platform: UNKNOWN
Requires-Dist: click
Requires-Dist: colorama
Requires-Dist: PyYAML
Requires-Dist: networkx
